taillight/__init__.py
taillight/signal.py
taillight/slot.py
taillight-0.5.1.dist-info/LICENSE
taillight-0.5.1.dist-info/METADATA
taillight-0.5.1.dist-info/WHEEL
taillight-0.5.1.dist-info/top_level.txt
taillight-0.5.1.dist-info/RECORD
