Metadata-Version: 2.1
Name: taillight
Version: 0.5.1
Summary: An implementation of signals and slots, with priorities.
Home-page: http://github.com/Elizafox/taillight
Author: Elizabeth Myers
Author-email: elizabeth@interlinked.me
Classifier: Development Status :: 4 - Beta
Classifier: Intended Audience :: Developers
Classifier: Topic :: Software Development
Classifier: Topic :: Software Development :: Libraries :: Python Modules
Classifier: Programming Language :: Python :: 3 :: Only
Classifier: Programming Language :: Python :: 3.5
Classifier: Programming Language :: Python :: 3.6
Classifier: Programming Language :: Python :: 3.7
Classifier: Programming Language :: Python :: 3.8
Classifier: Programming Language :: Python :: 3.9
Classifier: Programming Language :: Python :: 3.10
Classifier: Programming Language :: Python :: 3.11
Classifier: Operating System :: OS Independent
Classifier: License :: DFSG approved
License-File: LICENSE
